{
  "q_art_001": {
    "question": "Chi ha dipinto la Gioconda?",
    "correct": "Leonardo da Vinci",
    "wrong": ["Michelangelo", "Raffaello", "Botticelli"],
    "explanation": "Leonardo da Vinci dipinse la Gioconda tra il 1503 e il 1519."
  },
  "q_art_002": {
    "question": "Quale compositore scrisse la 'Nona Sinfonia'?",
    "correct": "Ludwig van Beethoven",
    "wrong": ["Mozart", "Bach", "Chopin"],
    "explanation": "La Nona Sinfonia di Beethoven, completata nel 1824, include la famosa 'Inno alla Gioia'."
  },
  "q_art_003": {
    "question": "In quale citta si trova il Museo del Louvre?",
    "correct": "Parigi",
    "wrong": ["Londra", "Roma", "Madrid"],
    "explanation": "Il Louvre a Parigi e il museo d'arte piu grande del mondo."
  },
  "q_art_004": {
    "question": "Chi ha scritto 'Romeo e Giulietta'?",
    "correct": "William Shakespeare",
    "wrong": ["Charles Dickens", "Jane Austen", "Oscar Wilde"],
    "explanation": "Shakespeare scrisse Romeo e Giulietta intorno al 1594-1596."
  },
  "q_art_005": {
    "question": "A quale movimento artistico apparteneva Salvador Dali?",
    "correct": "Surrealismo",
    "wrong": ["Impressionismo", "Cubismo", "Espressionismo"],
    "explanation": "Dali fu una figura di spicco del movimento surrealista, noto per le sue immagini sorprendenti."
  }
}
