{
  "q_art_001": {
    "question": "من رسم لوحة الموناليزا؟",
    "correct": "ليوناردو دا فينشي",
    "wrong": ["مايكل أنجلو", "رافائيل", "بوتيتشيلي"],
    "explanation": "رسم ليوناردو دا فينشي لوحة الموناليزا بين عامي 1503 و1519.",
    "hint": "فنان عصر النهضة الإيطالي الذي رسم أيضاً 'العشاء الأخير' وصمم آلات طيران."
  },
  "q_art_002": {
    "question": "أي ملحن كتب 'السيمفونية التاسعة'؟",
    "correct": "لودفيج فان بيتهوفن",
    "wrong": ["موزارت", "باخ", "شوبان"],
    "explanation": "اكتملت السيمفونية التاسعة لبيتهوفن عام 1824 وتتضمن 'نشيد الفرح' الشهير.",
    "hint": "ملحن ألماني أصيب بالصمم لكنه استمر في التأليف الموسيقي."
  },
  "q_art_003": {
    "question": "في أي مدينة يقع متحف اللوفر؟",
    "correct": "باريس",
    "wrong": ["لندن", "روما", "مدريد"],
    "explanation": "متحف اللوفر في باريس هو أكبر متحف فني في العالم.",
    "hint": "عاصمة فرنسا حيث يوجد هذا المتحف ذو الهرم الزجاجي الشهير."
  },
  "q_art_004": {
    "question": "من كتب 'روميو وجولييت'؟",
    "correct": "وليام شكسبير",
    "wrong": ["تشارلز ديكنز", "جين أوستن", "أوسكار وايلد"],
    "explanation": "كتب شكسبير روميو وجولييت حوالي عام 1594-1596.",
    "hint": "الكاتب الإنجليزي الأشهر الذي ولد في ستراتفورد وكتب 'هاملت' و'ماكبث'."
  },
  "q_art_005": {
    "question": "إلى أي حركة فنية انتمى سلفادور دالي؟",
    "correct": "السريالية",
    "wrong": ["الانطباعية", "التكعيبية", "التعبيرية"],
    "explanation": "كان دالي شخصية بارزة في الحركة السريالية المعروفة بصورها المذهلة.",
    "hint": "حركة فنية تستكشف اللاوعي والأحلام، ولوحته الشهيرة تظهر ساعات ذائبة."
  },
  "q_art_006": {
    "question": "من رسم لوحة 'ليلة مرصعة بالنجوم'؟",
    "correct": "فينسنت فان غوخ",
    "wrong": ["كلود مونيه", "بول سيزان", "إدغار ديغا"],
    "hint": "هذا الرسام الهولندي قطع جزءاً من أذنه.",
    "explanation": "رسم فان غوخ لوحة 'ليلة مرصعة بالنجوم' عام 1889 أثناء إقامته في مصح سان ريمي دو بروفانس."
  },
  "q_art_007": {
    "question": "أي آلة موسيقية تحتوي على 88 مفتاحاً؟",
    "correct": "البيانو",
    "wrong": ["الأورغن", "الهاربسيكورد", "الأكورديون"],
    "hint": "يحتوي على مفاتيح بيضاء وسوداء واخترع في إيطاليا حوالي عام 1700.",
    "explanation": "يحتوي البيانو الحديث القياسي على 52 مفتاحاً أبيض و36 أسود، أي 88 مفتاحاً في المجموع."
  },
  "q_art_008": {
    "question": "من نحت تمثال 'المفكر'؟",
    "correct": "أوغست رودان",
    "wrong": ["دوناتيلو", "بيرنيني", "هنري مور"],
    "hint": "يُلقب هذا النحات الفرنسي بأبي النحت الحديث.",
    "explanation": "أنشأ رودان تمثال 'المفكر' عام 1904، وكان في الأصل جزءاً من عمل أكبر يُسمى 'بوابات الجحيم'."
  },
  "q_art_009": {
    "question": "أي رواية تبدأ بعبارة 'نادوني إسماعيل'؟",
    "correct": "موبي ديك",
    "wrong": ["جزيرة الكنز", "الشيخ والبحر", "روبنسون كروزو"],
    "hint": "تروي هذه الرواية قصة هوس قبطان بحوت أبيض.",
    "explanation": "رواية موبي ديك لهيرمان ملفيل، نُشرت عام 1851، تبدأ بواحدة من أشهر الجمل في الأدب."
  },
  "q_art_010": {
    "question": "من ألّف 'الفصول الأربعة'؟",
    "correct": "أنطونيو فيفالدي",
    "wrong": ["يوهان سباستيان باخ", "جورج فريدريك هاندل", "فرانز شوبرت"],
    "hint": "هذا المؤلف الموسيقي الإيطالي من عصر الباروك كان كاهناً أحمر الشعر يُلقب بـ'الكاهن الأحمر'.",
    "explanation": "ألّف فيفالدي 'الفصول الأربعة' حوالي عام 1723، وهي مجموعة من أربعة كونشيرتوهات للكمان."
  }
}
