{
  "q_his_001": {
    "question": "第二次世界大戦は何年に終わりましたか？",
    "correct": "1945年",
    "wrong": [
      "1944年",
      "1946年",
      "1943年"
    ],
    "hint": "1940年代半ば、国際連合が設立されたのと同じ年に終わりました。",
    "explanation": "第二次世界大戦は1945年5月のドイツ降伏と9月の日本降伏で終結しました。"
  },
  "q_his_002": {
    "question": "アメリカ合衆国の初代大統領は誰ですか？",
    "correct": "ジョージ・ワシントン",
    "wrong": [
      "トーマス・ジェファーソン",
      "エイブラハム・リンカーン",
      "ジョン・アダムズ"
    ],
    "hint": "1ドル紙幣に顔が描かれている人物です。",
    "explanation": "ジョージ・ワシントンは1789年から1797年まで初代大統領を務めました。"
  },
  "q_his_003": {
    "question": "ギザのピラミッドを建設した古代文明はどれですか？",
    "correct": "古代エジプト",
    "wrong": [
      "ローマ",
      "ギリシャ",
      "メソポタミア"
    ],
    "hint": "ナイル川沿いに住み、ファラオに統治されていました。",
    "explanation": "ギザの大ピラミッドは紀元前2560年頃、クフ王のために建設されました。"
  },
  "q_his_004": {
    "question": "ベルリンの壁は何年に崩壊しましたか？",
    "correct": "1989年",
    "wrong": [
      "1987年",
      "1991年",
      "1985年"
    ],
    "hint": "1990年のドイツ統一の1年前に起こりました。",
    "explanation": "ベルリンの壁は1989年11月9日に崩壊し、冷戦終結の重要な転換点となりました。"
  },
  "q_his_005": {
    "question": "チンギス・ハーンが統治した帝国はどれですか？",
    "correct": "モンゴル帝国",
    "wrong": [
      "オスマン帝国",
      "ローマ帝国",
      "ペルシャ帝国"
    ],
    "hint": "中央アジアの草原地帯から始まった帝国です。",
    "explanation": "チンギス・ハーンは史上最大の連続した領土を持つモンゴル帝国を建設しました。"
  },
  "q_his_006": {
    "question": "初めて月面に降り立った人は誰ですか？",
    "correct": "ニール・アームストロング",
    "wrong": [
      "バズ・オルドリン",
      "ユーリ・ガガーリン",
      "ジョン・グレン"
    ],
    "hint": "「これは一人の人間にとっては小さな一歩だが、人類にとっては偉大な飛躍だ」と言った人物です。",
    "explanation": "ニール・アームストロングは1969年7月20日、アポロ11号のミッションで初めて月面を歩きました。"
  },
  "q_his_007": {
    "question": "1912年に処女航海で沈没した船は何ですか？",
    "correct": "RMSタイタニック",
    "wrong": [
      "RMSルシタニア",
      "HMSブリタニック",
      "SSアンドレア・ドーリア"
    ],
    "hint": "「沈まない船」と呼ばれ、北大西洋で氷山に衝突しました。",
    "explanation": "タイタニックは1912年4月15日に氷山に衝突して沈没し、1,500人以上が犠牲になりました。"
  },
  "q_his_008": {
    "question": "ルネサンスは何世紀に始まりましたか？",
    "correct": "14世紀",
    "wrong": [
      "12世紀",
      "16世紀",
      "15世紀"
    ],
    "hint": "1300年代のイタリアで、黒死病の大流行の直後に始まりました。",
    "explanation": "ルネサンスは14世紀にイタリアで始まり、中世から近代への文化的転換をもたらしました。"
  },
  "q_his_009": {
    "question": "ペニシリンを発見した人は誰ですか？",
    "correct": "アレクサンダー・フレミング",
    "wrong": [
      "ルイ・パスツール",
      "ロベルト・コッホ",
      "ジョゼフ・リスター"
    ],
    "hint": "1928年にペトリ皿に生えたカビから偶然発見しました。",
    "explanation": "アレクサンダー・フレミングは1928年にペニシリンを発見し、最初の抗生物質として医学に革命をもたらしました。"
  },
  "q_his_010": {
    "question": "エジプトのアレクサンドリアにあった古代の不思議は何ですか？",
    "correct": "灯台",
    "wrong": [
      "巨像",
      "空中庭園",
      "アルテミス神殿"
    ],
    "hint": "100メートル以上の高さで、港に入る船乗りを導いた建造物です。",
    "explanation": "アレクサンドリアの灯台（ファロス）は紀元前280年頃に建設され、古代世界で最も高い建造物の一つでした。"
  },
  "q_his_011": {
    "question": "イギリス初の女性首相は？",
    "correct": "マーガレット・サッチャー",
    "wrong": [
      "テリーザ・メイ",
      "ヴィクトリア女王",
      "エメリン・パンクハースト"
    ],
    "hint": "「鉄の女」の異名を持ち、1979年から1990年まで在任しました。",
    "explanation": "マーガレット・サッチャーは1979年にイギリス初の女性首相となりました。"
  },
  "q_his_012": {
    "question": "フランス革命が始まった年は？",
    "correct": "1789年",
    "wrong": [
      "1776年",
      "1804年",
      "1815年"
    ],
    "hint": "バスティーユ襲撃から始まり、ジョージ・ワシントンが初代アメリカ大統領になったのと同じ年です。",
    "explanation": "フランス革命は1789年7月14日のバスティーユ襲撃で始まりました。"
  },
  "q_his_013": {
    "question": "西暦79年のヴェスヴィオ火山噴火で埋もれた古代都市は？",
    "correct": "ポンペイ",
    "wrong": [
      "アテネ",
      "カルタゴ",
      "トロイ"
    ],
    "hint": "このローマの都市は火山灰の下に保存され、18世紀に再発見されました。",
    "explanation": "ポンペイはヴェスヴィオ火山の火山灰の下に埋もれました。"
  },
  "q_his_014": {
    "question": "中国を最初に統一した皇帝は誰ですか？",
    "correct": "始皇帝（秦の始皇帝）",
    "wrong": [
      "劉邦",
      "フビライ・ハン",
      "武則天"
    ],
    "hint": "彼は万里の長城の建設を命じ、有名な兵馬俑とともに埋葬されました。",
    "explanation": "始皇帝は紀元前221年に中国を統一し、秦王朝を樹立し、帝国全体の度量衡と文字を統一しました。"
  },
  "q_his_015": {
    "question": "チェルノブイリ原子力発電所事故は何年に発生しましたか？",
    "correct": "1986年",
    "wrong": [
      "1984年",
      "1988年",
      "1979年"
    ],
    "hint": "1980年代半ばのソ連ウクライナで発生し、スペースシャトル・チャレンジャー号が爆発したのと同じ年です。",
    "explanation": "チェルノブイリ事故は1986年4月26日に発生し、史上最悪の原子力発電所事故として残っています。"
  },
  "q_his_016": {
    "question": "中国と地中海を結んだ古代の交易路はどれですか？",
    "correct": "シルクロード",
    "wrong": [
      "スパイスルート",
      "琥珀の道",
      "乳香の道"
    ],
    "hint": "そこで取引された最も貴重な商品にちなんで名付けられました。",
    "explanation": "シルクロードは紀元前2世紀から東アジアと地中海を結んだ6,400km以上の交易路ネットワークです。"
  },
  "q_his_017": {
    "question": "大西洋を単独飛行で横断した最初の女性は誰ですか？",
    "correct": "アメリア・イアハート",
    "wrong": [
      "ハリエット・クインビー",
      "ベッシー・コールマン",
      "ジャクリーン・コクラン"
    ],
    "hint": "彼女は1937年に世界一周飛行を試みた際に謎の失踪を遂げました。",
    "explanation": "アメリア・イアハートは1932年5月20〜21日に大西洋単独横断飛行を達成しました。"
  },
  "q_his_018": {
    "question": "ロシア革命が始まったのは何年ですか？",
    "correct": "1917年",
    "wrong": [
      "1905年",
      "1914年",
      "1920年"
    ],
    "hint": "第一次世界大戦中に起こり、皇帝が退位しボリシェヴィキが権力を掌握しました。",
    "explanation": "1917年のロシア革命は二月革命と十月革命の2つの革命で構成されています。"
  },
  "q_his_019": {
    "question": "マチュ・ピチュを建設した文明はどれですか？",
    "correct": "インカ帝国",
    "wrong": [
      "アステカ帝国",
      "マヤ文明",
      "オルメカ文明"
    ],
    "hint": "この城塞はペルーのアンデス山脈の高地に位置しています。",
    "explanation": "マチュ・ピチュは15世紀にインカ帝国によって標高約2,430メートルに建設されました。"
  },
  "q_his_020": {
    "question": "ヨーロッパで活版印刷機を発明したのは誰ですか？",
    "correct": "ヨハネス・グーテンベルク",
    "wrong": [
      "ウィリアム・キャクストン",
      "アルドゥス・マヌティウス",
      "畢昇"
    ],
    "hint": "1440年頃のドイツでの彼の発明は、知識の普及に革命をもたらしました。",
    "explanation": "ヨハネス・グーテンベルクは1440年頃に活版印刷機を発明しました。"
  },
  "q_his_021": {
    "question": "歴史上、領土面積が最大だった帝国はどれですか？",
    "correct": "大英帝国",
    "wrong": [
      "モンゴル帝国",
      "ローマ帝国",
      "ロシア帝国"
    ],
    "hint": "この帝国については「日の沈まない帝国」と言われていました。",
    "explanation": "大英帝国は1920年の最盛期に約3,550万km²を支配し、世界の陸地面積の約4分の1を占めていました。"
  },
  "q_his_022": {
    "question": "アメリカ合衆国が独立を宣言したのは何年ですか？",
    "correct": "1776年",
    "wrong": [
      "1783年",
      "1774年",
      "1781年"
    ],
    "hint": "7月4日に採択され、1770年代後半のことで、フランス革命より10年以上前です。",
    "explanation": "アメリカ独立宣言は1776年7月4日に採択され、イギリスからの独立を宣言しました。"
  },
  "q_his_023": {
    "question": "ローマ帝国の初代皇帝は誰ですか？",
    "correct": "アウグストゥス",
    "wrong": [
      "ユリウス・カエサル",
      "ネロ",
      "ティベリウス"
    ],
    "hint": "オクタウィアヌスとして生まれ、ユリウス・カエサルの養子でした。",
    "explanation": "アウグストゥス（本名ガイウス・オクタウィウス）は紀元前27年にローマ初代皇帝となり、紀元14年まで統治してパクス・ロマーナの時代を築きました。"
  },
  "q_his_024": {
    "question": "世界一周航海を初めて成し遂げた探検隊を率いたのは誰ですか？",
    "correct": "フェルディナンド・マゼラン",
    "wrong": [
      "クリストファー・コロンブス",
      "ジェームズ・クック",
      "ヴァスコ・ダ・ガマ"
    ],
    "hint": "このポルトガルの探検家は1519年にスペインから5隻の船で出航しましたが、フィリピンで殺害され、乗組員が彼なしで航海を完了しました。",
    "explanation": "フェルディナンド・マゼランの探検隊（1519〜1522年）が初めて地球を一周しました。マゼラン自身は1521年にフィリピンで死亡し、フアン・セバスティアン・エルカーノが航海を完了しました。"
  },
  "q_his_025": {
    "question": "非暴力抵抗を通じてインドの独立運動を率いたのは誰ですか？",
    "correct": "マハトマ・ガンディー",
    "wrong": [
      "ジャワハルラール・ネルー",
      "スバス・チャンドラ・ボース",
      "バガット・シン"
    ],
    "hint": "インドで「国父」として知られ、1930年の有名な塩の行進を率い、常に手紡ぎの質素な布をまとっていました。",
    "explanation": "マハトマ・ガンディーは非暴力的市民的不服従を通じて1947年のインド独立をイギリスから勝ち取りました。彼の哲学は世界中の公民権運動に影響を与えました。"
  },
  "q_his_026": {
    "question": "最古の文字体系の一つである楔形文字を発明した古代文明はどれですか？",
    "correct": "シュメール人",
    "wrong": [
      "古代エジプト人",
      "フェニキア人",
      "インダス文明"
    ],
    "hint": "メソポタミア（現在のイラク）に住み、紀元前3400年頃に湿った粘土板にくさび形の印を押しました。",
    "explanation": "メソポタミアのシュメール人は紀元前3400年頃に楔形文字を発明しました。当初は記録管理に使われ、やがて文学、法律、科学を表現するようになりました。"
  },
  "q_his_027": {
    "question": "ローマ人がブリテン島北部に築いた防壁の名前は何ですか？",
    "correct": "ハドリアヌスの長城",
    "wrong": [
      "アントニヌスの長城",
      "万里の長城",
      "オファの防塁"
    ],
    "hint": "紀元122年にローマ皇帝の命令で建設されたこの73マイルの石壁は、海岸から海岸まで延び、帝国のブリテン島における北の国境を示していました。",
    "explanation": "ハドリアヌスの長城はハドリアヌス帝の下で紀元122年に建設が始まりました。イングランド北部を横断する73マイル（117km）にわたり、現在はユネスコ世界遺産に登録されています。"
  },
  "q_his_028": {
    "question": "第一次世界大戦を公式に終結させた条約は何でしょう？",
    "correct": "ヴェルサイユ条約",
    "wrong": [
      "パリ条約",
      "ゲント条約",
      "トルデシリャス条約"
    ],
    "hint": "この条約は1919年にフランスの有名な宮殿で署名されました。",
    "explanation": "ヴェルサイユ条約は1919年6月28日にヴェルサイユ宮殿の鏡の間で署名されました。ドイツに多額の賠償金を課し、ヨーロッパの国境を再編しました。"
  },
  "q_his_029": {
    "question": "古代エジプト最後のファラオは誰でしょう？",
    "correct": "クレオパトラ7世",
    "wrong": [
      "ネフェルティティ",
      "ハトシェプスト",
      "ラメセス2世"
    ],
    "hint": "彼女はユリウス・カエサルとマルクス・アントニウスの両方とロマンスがありました。",
    "explanation": "クレオパトラ7世は紀元前51年から30年までエジプトを統治しました。彼女の死後、エジプトはローマ帝国の属州となり、3,000年以上のファラオの統治に終止符が打たれました。"
  },
  "q_his_030": {
    "question": "ロンドン大火は何年に起こりましたか？",
    "correct": "1666",
    "wrong": [
      "1606",
      "1712",
      "1588"
    ],
    "hint": "1660年代半ば、チャールズ2世の治世にプディング・レーンのパン屋から出火しました。",
    "explanation": "1666年のロンドン大火は4日間で13,000軒以上の家屋と87の教会を焼失させました。"
  },
  "q_his_031": {
    "question": "海路でインドに最初に到達したポルトガルの探検家は誰ですか？",
    "correct": "ヴァスコ・ダ・ガマ",
    "wrong": [
      "バルトロメウ・ディアス",
      "ペドロ・アルヴァレス・カブラル",
      "エンリケ航海王子"
    ],
    "hint": "喜望峰を回って航海しました。",
    "explanation": "ヴァスコ・ダ・ガマは1498年にインドのカリカットに到着しました。"
  },
  "q_his_032": {
    "question": "バビロンにあったとされる古代世界の不思議は何ですか？",
    "correct": "空中庭園",
    "wrong": [
      "ロドス島の巨像",
      "大図書館",
      "バベルの塔"
    ],
    "hint": "伝説によると、ネブカドネザル2世がホームシックの妻のために建てたと言われています。",
    "explanation": "バビロンの空中庭園は、世界七不思議の中で唯一その存在が議論されているものです。"
  },
  "q_his_033": {
    "question": "1848年にフリードリヒ・エンゲルスと共に『共産党宣言』を共同執筆したのは誰ですか？",
    "correct": "カール・マルクス",
    "wrong": [
      "アダム・スミス",
      "ジョン・スチュアート・ミル",
      "ゲオルク・ヘーゲル"
    ],
    "hint": "主著『資本論』でも知られています。",
    "explanation": "カール・マルクスはエンゲルスと共に『共産党宣言』を共同執筆しました。"
  }
}
